difflogtest/__init__.py
difflogtest/cli.py
difflogtest/core.py
difflogtest/decorators.py
difflogtest/logging/__init__.py
difflogtest/logging/core.py
difflogtest/logging/utils.py
difflogtest/utils/__init__.py
difflogtest/utils/mode.py
difflogtest/utils/path.py
difflogtest/utils/replacements.py
difflogtest/utils/strings.py
difflogtest-0.0.1.dist-info/METADATA
difflogtest-0.0.1.dist-info/WHEEL
difflogtest-0.0.1.dist-info/entry_points.txt
difflogtest-0.0.1.dist-info/RECORD
