Metadata-Version: 2.4
Name: difflogtest
Version: 0.0.1
Summary: A unittest framework for comparing outputs with logged expectations.
Author-email: Andres <me@afromero.co>
Requires-Python: >=3.10
Requires-Dist: dotenv>=0.9.9
Requires-Dist: gitpython>=3.1.0
Requires-Dist: json5>=0.10.0
Requires-Dist: natsort>=8.4.0
Requires-Dist: pip>=25.2
Requires-Dist: pydantic>=2.10.2
Requires-Dist: python-dotenv>=0.19.0
Requires-Dist: pytz>=2023.3
Requires-Dist: rich>=13.9.4
Requires-Dist: torch
Requires-Dist: torchvision
Requires-Dist: tyro<0.10,>=0.9.2
Requires-Dist: wget>=3.2
